davvy
