Metadata-Version: 1.0
Name: davvy
Version: 0.1.1
Summary: A Django application for building WebDAV services
Home-page: https://github.com/unbit/davvy
Author: Unbit
Author-email: info@unbit.com
License: MIT License
Platform: UNKNOWN
